automate_ws-0.9.1.data/data/etc/automate-home/static/blockly_compressed.js
automate_ws-0.9.1.data/data/etc/automate-home/static/blocks_compressed.js
automate_ws-0.9.1.data/data/etc/automate-home/static/collection.css
automate_ws-0.9.1.data/data/etc/automate-home/static/history.css
automate_ws-0.9.1.data/data/etc/automate-home/static/homino.css
automate_ws-0.9.1.data/data/etc/automate-home/static/homino.js
automate_ws-0.9.1.data/data/etc/automate-home/static/icon.svg
automate_ws-0.9.1.data/data/etc/automate-home/static/icon2.svg
automate_ws-0.9.1.data/data/etc/automate-home/static/icon_128x128_blu.png
automate_ws-0.9.1.data/data/etc/automate-home/static/icon_just_border_128x128_blu.png
automate_ws-0.9.1.data/data/etc/automate-home/static/index.css
automate_ws-0.9.1.data/data/etc/automate-home/static/javascript_compressed.js
automate_ws-0.9.1.data/data/etc/automate-home/static/python_compressed.js
automate_ws-0.9.1.data/data/etc/automate-home/static/block/appliance.js
automate_ws-0.9.1.data/data/etc/automate-home/static/block/event.js
automate_ws-0.9.1.data/data/etc/automate-home/static/block/knx.js
automate_ws-0.9.1.data/data/etc/automate-home/static/block/light_event.js
automate_ws-0.9.1.data/data/etc/automate-home/static/block/scheduler.js
automate_ws-0.9.1.data/data/etc/automate-home/static/generator/appliance.js
automate_ws-0.9.1.data/data/etc/automate-home/static/generator/event.js
automate_ws-0.9.1.data/data/etc/automate-home/static/generator/knx.js
automate_ws-0.9.1.data/data/etc/automate-home/static/generator/light_event.js
automate_ws-0.9.1.data/data/etc/automate-home/static/generator/scheduler.js
automate_ws-0.9.1.data/data/etc/automate-home/static/media/appliance.js
automate_ws-0.9.1.data/data/etc/automate-home/static/media/event.js
automate_ws-0.9.1.data/data/etc/automate-home/static/media/knx.js
automate_ws-0.9.1.data/data/etc/automate-home/static/media/light_event.js
automate_ws-0.9.1.data/data/etc/automate-home/static/media/scheduler.js
automate_ws-0.9.1.dist-info/COPYING
automate_ws-0.9.1.dist-info/METADATA
automate_ws-0.9.1.dist-info/WHEEL
automate_ws-0.9.1.dist-info/top_level.txt
automate_ws-0.9.1.dist-info/RECORD
